tests/__init__.py
tests/test_api.py
tests/test_utils.py
tests/graphql/__init__.py
tests/graphql/test_client.py
vouched/__init__.py
vouched/api.py
vouched/errors.py
vouched/utils.py
vouched/graphql/__init__.py
vouched/graphql/client.py
vouched/graphql/schemas.py
vouched/graphql/utils.py
vouched_python-0.0.5b10.dist-info/LICENSE
vouched_python-0.0.5b10.dist-info/METADATA
vouched_python-0.0.5b10.dist-info/WHEEL
vouched_python-0.0.5b10.dist-info/top_level.txt
vouched_python-0.0.5b10.dist-info/RECORD
