Metadata-Version: 2.1
Name: vouched-python
Version: 0.0.5b10
Summary: Vouched Client
Home-page: https://github.com/vouched/vouched-python
Author: John Cao
Author-email: cao@vouched.id
License: UNKNOWN
Platform: UNKNOWN
Classifier: Programming Language :: Python :: 3
Classifier: License :: OSI Approved :: Academic Free License (AFL)
Classifier: Operating System :: OS Independent
Requires-Dist: wheel (==0.32.2)
Requires-Dist: opencv-python (==3.4.4.19)
Requires-Dist: gql (==0.1.0)
Requires-Dist: pyopenssl (==18.0.0)
Requires-Dist: ndg-httpsclient (==0.5.1)
Requires-Dist: pyasn1 (==0.4.4)
Requires-Dist: python-magic (==0.4.15)
Requires-Dist: pytest (==3.9.2)
Requires-Dist: requests[security] (==2.20.0)
Requires-Dist: requests-mock (==1.5.2)
